sepy/ConnectionHandler.py
sepy/Exceptions.py
sepy/SAPObject.py
sepy/SEPA.py
sepy/__init__.py
sepy/tablaze.py
sepy/ysap_template.sap
sepy/tests/SepyTestSecure_SAP.py
sepy/tests/SepyTestUnsecure_SAP.py
sepy/tests/__init__.py
sepy/tests/testSecure.ysap
sepy/tests/testUnsecure.ysap
sepy-0.43.2.1.dist-info/LICENSE
sepy-0.43.2.1.dist-info/METADATA
sepy-0.43.2.1.dist-info/WHEEL
sepy-0.43.2.1.dist-info/top_level.txt
sepy-0.43.2.1.dist-info/RECORD
