Metadata-Version: 2.1
Name: sepy
Version: 0.43.2.1
Summary: Client-side libraries for the SEPA platform (Python3) 
Home-page: https://github.com/fr4ncidir/SEPA-python3-APIs
Author: Fabio Viola, Francesco Antoniazzi
Author-email: fabio.viola@unibo.it, francesco.antoniazzi1991@gmail.com
License: GPLv3
Platform: UNKNOWN
Requires-Dist: websocket-client
Requires-Dist: argparse
Requires-Dist: prettytable
Requires-Dist: pyyaml
Requires-Dist: jinja2
